i2c_adapter/__init__.py
i2c_adapter/py.typed
i2c_adapter-0.2.20.dist-info/METADATA
i2c_adapter-0.2.20.dist-info/WHEEL
i2c_adapter-0.2.20.dist-info/licenses/LICENSE
i2c_adapter-0.2.20.dist-info/RECORD
