Metadata-Version: 2.1
Name: i2c_adapter
Version: 0.2.20
Summary: A simple USB to I2C adapter that works.
Project-URL: Homepage, https://github.com/zapta/i2c_adapter
Project-URL: Documentation, https://i2c-adapter.readthedocs.io/en/latest
Project-URL: Repository, https://github.com/zapta/i2c_adapter.git
Project-URL: Bug Tracker, https://github.com/zapta/i2c_adapter/issues
Author-email: Zapta <zapta@zapta.com>
License-File: LICENSE
Classifier: Development Status :: 5 - Production/Stable
Classifier: License :: CC0 1.0 Universal (CC0 1.0) Public Domain Dedication
Classifier: Operating System :: OS Independent
Classifier: Programming Language :: Python :: 3
Requires-Python: >=3.7
Requires-Dist: pyserial>=3.5
